0x_sra_client-4.0.0-py3.7-nspkg.pth
zero_ex/sra_client/__init__.py
zero_ex/sra_client/api_client.py
zero_ex/sra_client/configuration.py
zero_ex/sra_client/rest.py
zero_ex/sra_client/api/__init__.py
zero_ex/sra_client/api/default_api.py
zero_ex/sra_client/models/__init__.py
zero_ex/sra_client/models/order_schema.py
zero_ex/sra_client/models/paginated_collection_schema.py
zero_ex/sra_client/models/relayer_api_asset_data_pairs_response_schema.py
zero_ex/sra_client/models/relayer_api_asset_data_trade_info_schema.py
zero_ex/sra_client/models/relayer_api_error_response_schema.py
zero_ex/sra_client/models/relayer_api_error_response_schema_validation_errors.py
zero_ex/sra_client/models/relayer_api_fee_recipients_response_schema.py
zero_ex/sra_client/models/relayer_api_order_config_payload_schema.py
zero_ex/sra_client/models/relayer_api_order_config_response_schema.py
zero_ex/sra_client/models/relayer_api_order_schema.py
zero_ex/sra_client/models/relayer_api_orderbook_response_schema.py
zero_ex/sra_client/models/relayer_api_orders_channel_subscribe_payload_schema.py
zero_ex/sra_client/models/relayer_api_orders_channel_subscribe_schema.py
zero_ex/sra_client/models/relayer_api_orders_channel_update_schema.py
zero_ex/sra_client/models/relayer_api_orders_response_schema.py
zero_ex/sra_client/models/signed_order_schema.py
0x_sra_client-4.0.0.dist-info/METADATA
0x_sra_client-4.0.0.dist-info/WHEEL
0x_sra_client-4.0.0.dist-info/namespace_packages.txt
0x_sra_client-4.0.0.dist-info/top_level.txt
0x_sra_client-4.0.0.dist-info/RECORD
