Metadata-Version: 2.1
Name: 0x-sra-client
Version: 4.0.0
Summary: Standard Relayer REST API Client
Home-page: https://github.com/0xproject/0x-monorepo/tree/development/python-packages/sra_client
Author: F. Eugene Aumson
Author-email: feuGeneA@users.noreply.github.com
License: UNKNOWN
Keywords: OpenAPI,OpenAPI-Generator,Standard Relayer REST API
Platform: UNKNOWN
Requires-Dist: urllib3 (>=1.15)
Requires-Dist: six (>=1.10)
Requires-Dist: certifi
Requires-Dist: python-dateutil
Provides-Extra: dev
Requires-Dist: 0x-contract-artifacts ; extra == 'dev'
Requires-Dist: 0x-contract-addresses ; extra == 'dev'
Requires-Dist: 0x-contract-wrappers ; extra == 'dev'
Requires-Dist: 0x-order-utils ; extra == 'dev'
Requires-Dist: web3 ; extra == 'dev'
Requires-Dist: bandit ; extra == 'dev'
Requires-Dist: black ; extra == 'dev'
Requires-Dist: coverage ; extra == 'dev'
Requires-Dist: coveralls ; extra == 'dev'
Requires-Dist: pycodestyle ; extra == 'dev'
Requires-Dist: pydocstyle ; extra == 'dev'
Requires-Dist: pylint ; extra == 'dev'
Requires-Dist: pytest ; extra == 'dev'
Requires-Dist: sphinx ; extra == 'dev'
Requires-Dist: sphinx-autodoc-typehints ; extra == 'dev'
